fstringify/__init__.py
fstringify/__main__.py
fstringify/api.py
fstringify/format.py
fstringify/process.py
fstringify/transform.py
fstringify/utils.py
fstringify-0.1.14.dist-info/DESCRIPTION.rst
fstringify-0.1.14.dist-info/METADATA
fstringify-0.1.14.dist-info/RECORD
fstringify-0.1.14.dist-info/WHEEL
fstringify-0.1.14.dist-info/entry_points.txt
fstringify-0.1.14.dist-info/metadata.json
fstringify-0.1.14.dist-info/top_level.txt
