Metadata-Version: 2.0
Name: fstringify
Version: 0.1.14
Summary: CLI tool to convert a python project's old style strings to f-strings.
Home-page: https://github.com/jacktasia/fstringify
Author: Jack Angers
Author-email: jacktasia@gmail.com
License: GNU General Public License v3.0
Download-URL: https://github.com/jacktasia/fstringify/tarball/0.1.14
Keywords: utility,strings
Platform: UNKNOWN
Classifier: Programming Language :: Python
Classifier: Programming Language :: Python :: 3
Classifier: Programming Language :: Python :: 3.6
Classifier: Programming Language :: Python :: 3.7
Classifier: Topic :: Software Development :: Libraries :: Python Modules
Classifier: Topic :: Utilities
Requires-Dist: astor (==0.7.1)
Requires-Dist: black (==19.3b0)
